{
    "api_alias": "kcapi",
    "api_package": "gitlab.com/KopiCloud/kopicloud-ad-tf-provider/api",
    "package": "provider",
    "data_sources" : [
        {
            "name": "AllComputers",
            "terraform": {
                "name": "kopicloud_all_computers",
                "arguments": []
            },
            "schema_function": "schemaOfComputerListADApiResult",
            "element_name": "Computer",
            "crud": {
                "read": {
                    "api_function": {
                        "name": "GetApiComputersAllWithResponse",
                        "arguments": [],
                        "params": {
                            "name": "GetApiComputersAllParams",
                            "fields": []
                        }
                    },                
                    "api_to_terraform": "ComputerListADApiResultToTerraform",
                    "result": {
                        "name": "computer_list",
                        "id": "all_computers"                    
                    }
                }
            }
        }
   ]
}